requests_verbose/__init__.py
requests_verbose-0.1.0.dist-info/LICENSE
requests_verbose-0.1.0.dist-info/METADATA
requests_verbose-0.1.0.dist-info/WHEEL
requests_verbose-0.1.0.dist-info/top_level.txt
requests_verbose-0.1.0.dist-info/RECORD
