Metadata-Version: 2.1
Name: requests-verbose
Version: 0.1.0
Summary: Convert requests.Response into a string representing an HTTP-request and its response
Author-email: Vitaly Samigullin <vrs@pilosus.org>
License: MIT
Project-URL: Source code, https://github.com/pilosus/requests-verbose/
Project-URL: Issue tracker, https://github.com/pilosus/requests-verbose/issues
Classifier: Programming Language :: Python :: 3
Classifier: Intended Audience :: Developers
Classifier: Topic :: Internet :: WWW/HTTP
Requires-Python: >=3.9
License-File: LICENSE
Requires-Dist: requests<3
